nfts/__init__.py
nfts/cli.py
nfts/data.py
nfts/dataset.py
nfts/datastore.py
nfts/derive.py
nfts/enrich.py
nfts/materialize.py
nfts-0.0.2.dist-info/METADATA
nfts-0.0.2.dist-info/WHEEL
nfts-0.0.2.dist-info/entry_points.txt
nfts-0.0.2.dist-info/top_level.txt
nfts-0.0.2.dist-info/RECORD
