Metadata-Version: 2.1
Name: nfts
Version: 0.0.2
Summary: Tools to build, update, and interact with the Moonstream NFTs dataset
Home-page: https://github.com/bugout-dev/moonstream
Author: Bugout.dev
Author-email: engineers@bugout.dev
License: Apache License 2.0
Platform: all
Classifier: Development Status :: 2 - Pre-Alpha
Classifier: Intended Audience :: Developers
Classifier: Natural Language :: English
Classifier: Programming Language :: Python
Classifier: Programming Language :: Python :: 3
Classifier: Programming Language :: Python :: 3.8
Classifier: Programming Language :: Python :: Implementation :: CPython
Classifier: Topic :: Software Development :: Libraries
Classifier: Topic :: Software Development :: Libraries :: Python Modules
Requires-Python: >=3.6
Requires-Dist: moonstreamdb
Requires-Dist: humbug
Requires-Dist: pandas
Requires-Dist: requests
Requires-Dist: tqdm
Requires-Dist: web3
Provides-Extra: dev
Requires-Dist: black ; extra == 'dev'
Requires-Dist: mypy ; extra == 'dev'
Requires-Dist: types-requests ; extra == 'dev'
Provides-Extra: distribute
Requires-Dist: setuptools ; extra == 'distribute'
Requires-Dist: twine ; extra == 'distribute'
Requires-Dist: wheel ; extra == 'distribute'
